airflow/__init__.py
airflow/airflow-kpo-extension.py
airflow_mlops-0.0.1.dist-info/LICENSE
airflow_mlops-0.0.1.dist-info/METADATA
airflow_mlops-0.0.1.dist-info/WHEEL
airflow_mlops-0.0.1.dist-info/top_level.txt
airflow_mlops-0.0.1.dist-info/RECORD
